bench.py
webenchmark-1.0.10.dist-info/METADATA
webenchmark-1.0.10.dist-info/RECORD
webenchmark-1.0.10.dist-info/WHEEL
webenchmark-1.0.10.dist-info/entry_points.txt
webenchmark-1.0.10.dist-info/top_level.txt
